ehf_invoice/__init__.py
ehf_invoice/admin.py
ehf_invoice/apps.py
ehf_invoice/urls.py
ehf_invoice/views.py
ehf_invoice/management/commands/__init__.py
ehf_invoice/management/commands/load_invoice.py
ehf_invoice/management/commands/lookup_supplier.py
ehf_invoice/migrations/0001_initial.py
ehf_invoice/migrations/0002_related_name.py
ehf_invoice/migrations/0003_invoice_credit.py
ehf_invoice/migrations/0004_mime_length.py
ehf_invoice/migrations/0005_supplier_alternate_id.py
ehf_invoice/migrations/__init__.py
ehf_invoice/models/Attachment.py
ehf_invoice/models/Customer.py
ehf_invoice/models/Invoice.py
ehf_invoice/models/InvoiceLine.py
ehf_invoice/models/SerialNumber.py
ehf_invoice/models/Supplier.py
ehf_invoice/models/__init__.py
ehf_invoice/parser/Attachment.py
ehf_invoice/parser/CreditNoteLine.py
ehf_invoice/parser/InvoiceLine.py
ehf_invoice/parser/InvoiceXML.py
ehf_invoice/parser/Party.py
ehf_invoice/parser/__init__.py
ehf_invoice/static/ehf_invoice/invoice.css
ehf_invoice/templates/ehf_invoice/base.html
ehf_invoice/templates/ehf_invoice/index.html
ehf_invoice/templates/ehf_invoice/invoice.html
ehf_invoice/templates/ehf_invoice/invoices.html
ehf_invoice/templates/ehf_invoice/supplier.html
ehf_invoice/templates/ehf_invoice/suppliers.html
tests/__init__.py
tests/test_import.py
tests/test_parser.py
tests/test_settings.py
django_ehf_import-1.7.dist-info/LICENSE
django_ehf_import-1.7.dist-info/METADATA
django_ehf_import-1.7.dist-info/WHEEL
django_ehf_import-1.7.dist-info/top_level.txt
django_ehf_import-1.7.dist-info/RECORD
